re_cue-0.3.4.dist-info/licenses/LICENSE
reverse_engineer/__init__.py
reverse_engineer/__main__.py
reverse_engineer/analyzer.py
reverse_engineer/boundary_enhancer.py
reverse_engineer/cache_manager.py
reverse_engineer/cli.py
reverse_engineer/config_wizard.py
reverse_engineer/diagram_generator.py
reverse_engineer/generators.py
reverse_engineer/interactive_editor.py
reverse_engineer/optimization.py
reverse_engineer/optimized_analyzer.py
reverse_engineer/phase_manager.py
reverse_engineer/progress_tracker.py
reverse_engineer/utils.py
reverse_engineer/analysis/__init__.py
reverse_engineer/analysis/actors/__init__.py
reverse_engineer/analysis/actors/actor_mapper.py
reverse_engineer/analysis/boundaries/__init__.py
reverse_engineer/analysis/boundaries/external_system_detector.py
reverse_engineer/analysis/boundaries/system_mapper.py
reverse_engineer/analysis/business_process/__init__.py
reverse_engineer/analysis/business_process/process_identifier.py
reverse_engineer/analysis/communication/__init__.py
reverse_engineer/analysis/communication/pattern_detector.py
reverse_engineer/analysis/discovery/__init__.py
reverse_engineer/analysis/git/__init__.py
reverse_engineer/analysis/git/changelog_generator.py
reverse_engineer/analysis/git/git_analyzer.py
reverse_engineer/analysis/journey/__init__.py
reverse_engineer/analysis/journey/journey_analyzer.py
reverse_engineer/analysis/naming/__init__.py
reverse_engineer/analysis/naming/use_case_namer.py
reverse_engineer/analysis/relationships/__init__.py
reverse_engineer/analysis/relationships/relationship_mapper.py
reverse_engineer/analysis/security/__init__.py
reverse_engineer/analysis/security/security_analyzer.py
reverse_engineer/analysis/structure/__init__.py
reverse_engineer/analysis/structure/package_analyzer.py
reverse_engineer/analysis/traceability/__init__.py
reverse_engineer/analysis/traceability/traceability_analyzer.py
reverse_engineer/analysis/transaction/__init__.py
reverse_engineer/analysis/transaction/transaction_analyzer.py
re_cue-0.3.4.dist-info/METADATA
re_cue-0.3.4.dist-info/WHEEL
re_cue-0.3.4.dist-info/entry_points.txt
re_cue-0.3.4.dist-info/top_level.txt
re_cue-0.3.4.dist-info/RECORD
