Metadata-Version: 2.4
Name: re-cue
Version: 0.3.4
Summary: RE-cue: Universal reverse engineering toolkit for multi-framework codebases
Home-page: https://github.com/cue-3/re-cue
Author: RE-cue Project
Author-email: 
License: MIT
Project-URL: Homepage, https://github.com/cue-3/re-cue
Project-URL: Documentation, https://cue-3.github.io/re-cue/
Project-URL: Repository, https://github.com/cue-3/re-cue
Project-URL: Bug Tracker, https://github.com/cue-3/re-cue/issues
Project-URL: Issue Tracker, https://github.com/cue-3/re-cue/issues
Project-URL: Changelog, https://github.com/cue-3/re-cue/blob/main/docs/releases/CHANGELOG.md
Project-URL: Source Code, https://github.com/cue-3/re-cue
Project-URL: Discussions, https://github.com/cue-3/re-cue/discussions
Keywords: reverse-engineering,documentation,api,openapi,specification,code-analysis
Classifier: Development Status :: 5 - Production/Stable
Classifier: Intended Audience :: Developers
Classifier: Intended Audience :: Information Technology
Classifier: Intended Audience :: System Administrators
Classifier: License :: OSI Approved :: MIT License
Classifier: Operating System :: OS Independent
Classifier: Programming Language :: Python :: 3
Classifier: Programming Language :: Python :: 3.9
Classifier: Programming Language :: Python :: 3.10
Classifier: Programming Language :: Python :: 3.11
Classifier: Programming Language :: Python :: 3.12
Classifier: Programming Language :: Python :: 3 :: Only
Classifier: Topic :: Software Development :: Documentation
Classifier: Topic :: Software Development :: Code Generators
Classifier: Topic :: Software Development :: Quality Assurance
Classifier: Topic :: Software Development :: Libraries :: Python Modules
Classifier: Topic :: Utilities
Classifier: Typing :: Typed
Requires-Python: >=3.9
License-File: LICENSE
Requires-Dist: jinja2>=3.0.0
Requires-Dist: pyyaml>=6.0
Dynamic: home-page
Dynamic: license-file
Dynamic: requires-python
